baseball_stats_python/__about__.py
baseball_stats_python/__init__.py
baseball_stats_python/constants/__init__.py
baseball_stats_python/constants/common.py
baseball_stats_python/enums/__init__.py
baseball_stats_python/enums/enum_base.py
baseball_stats_python/enums/minor.py
baseball_stats_python/enums/statcast.py
baseball_stats_python/enums/statcast_leaderboard.py
baseball_stats_python/statcast/__init__.py
baseball_stats_python/statcast/catcher_throwing.py
baseball_stats_python/statcast/minor_statcast_search.py
baseball_stats_python/statcast/mlbam_id_search.py
baseball_stats_python/statcast/runner_basestealing.py
baseball_stats_python/statcast/runner_extra_bases_taken.py
baseball_stats_python/statcast/statcast_search.py
baseball_stats_python/utils/minor.py
baseball_stats_python/utils/statcast.py
baseball_stats_python/utils/statcast_leaderboard.py
baseball_stats_python/utils/utils.py
baseball_stats_python-0.2.3.dist-info/METADATA
baseball_stats_python-0.2.3.dist-info/WHEEL
baseball_stats_python-0.2.3.dist-info/licenses/LICENSE
baseball_stats_python-0.2.3.dist-info/RECORD
