Metadata-Version: 2.4
Name: baseball-stats-python
Version: 0.2.3
Summary: A python pacakge for getting baseball stats
Project-URL: Homepage, https://github.com/ss77995ss/baseball-stats-python
Project-URL: Issues, https://github.com/ss77995ss/baseball-stats-python/issues
Author-email: Li-Hsuan Hsieh <ss77995ss@gmail.com>
License-File: LICENSE
Classifier: License :: OSI Approved :: MIT License
Classifier: Operating System :: OS Independent
Classifier: Programming Language :: Python :: 3
Requires-Python: >=3.8
